starknet_py/__init__.py
starknet_py/abi/__init__.py
starknet_py/abi/model.py
starknet_py/abi/parser.py
starknet_py/abi/schemas.py
starknet_py/abi/shape.py
starknet_py/abi/v1/__init__.py
starknet_py/abi/v1/core_structures.json
starknet_py/abi/v1/model.py
starknet_py/abi/v1/parser.py
starknet_py/abi/v1/parser_transformer.py
starknet_py/abi/v1/schemas.py
starknet_py/abi/v1/shape.py
starknet_py/abi/v2/__init__.py
starknet_py/abi/v2/model.py
starknet_py/abi/v2/parser.py
starknet_py/abi/v2/parser_transformer.py
starknet_py/abi/v2/schemas.py
starknet_py/abi/v2/shape.py
starknet_py/cairo/__init__.py
starknet_py/cairo/data_types.py
starknet_py/cairo/deprecated_parse/__init__.py
starknet_py/cairo/deprecated_parse/cairo_types.py
starknet_py/cairo/deprecated_parse/parser.py
starknet_py/cairo/deprecated_parse/parser_transformer.py
starknet_py/cairo/felt.py
starknet_py/cairo/type_parser.py
starknet_py/cairo/v1/__init__.py
starknet_py/cairo/v1/type_parser.py
starknet_py/cairo/v2/__init__.py
starknet_py/cairo/v2/type_parser.py
starknet_py/common.py
starknet_py/conftest.py
starknet_py/constants.py
starknet_py/contract.py
starknet_py/hash/__init__.py
starknet_py/hash/address.py
starknet_py/hash/casm_class_hash.py
starknet_py/hash/class_hash.py
starknet_py/hash/selector.py
starknet_py/hash/sierra_class_hash.py
starknet_py/hash/storage.py
starknet_py/hash/transaction.py
starknet_py/hash/utils.py
starknet_py/net/__init__.py
starknet_py/net/account/__init__.py
starknet_py/net/account/account.py
starknet_py/net/account/account_deployment_result.py
starknet_py/net/account/base_account.py
starknet_py/net/client.py
starknet_py/net/client_errors.py
starknet_py/net/client_models.py
starknet_py/net/client_utils.py
starknet_py/net/full_node_client.py
starknet_py/net/gateway_client.py
starknet_py/net/http_client.py
starknet_py/net/models/__init__.py
starknet_py/net/models/address.py
starknet_py/net/models/chains.py
starknet_py/net/models/transaction.py
starknet_py/net/models/typed_data.py
brine_starknet_py-0.18.7.dist-info/LICENSE.txt
brine_starknet_py-0.18.7.dist-info/METADATA
brine_starknet_py-0.18.7.dist-info/WHEEL
brine_starknet_py-0.18.7.dist-info/RECORD
