Metadata-Version: 2.1
Name: brine-starknet-py
Version: 0.18.7
Summary: A python SDK for Starknet
Home-page: https://github.com/software-mansion/starknet.py
License: MIT
Author: Tomasz Rejowski
Author-email: tomasz.rejowski@swmansion.com
Requires-Python: >=3.8,<3.12
Classifier: License :: OSI Approved :: MIT License
Classifier: Programming Language :: Python :: 3
Classifier: Programming Language :: Python :: 3.8
Classifier: Programming Language :: Python :: 3.9
Classifier: Programming Language :: Python :: 3.10
Classifier: Programming Language :: Python :: 3.11
Provides-Extra: docs
Requires-Dist: aiohttp (>=3.7.4,<4.0.0)
Requires-Dist: asgiref (>=3.4.1,<4.0.0)
Requires-Dist: crypto-cpp-py (>=1.4.0,<2.0.0)
Requires-Dist: enum-tools[sphinx] (==0.10.0) ; extra == "docs"
Requires-Dist: furo (>=2023.5.20,<2024.0.0) ; extra == "docs"
Requires-Dist: lark (>=1.1.5,<2.0.0)
Requires-Dist: marshmallow (>=3.15.0,<4.0.0)
Requires-Dist: marshmallow-dataclass (<8.5.0)
Requires-Dist: marshmallow-oneofschema (>=3.0.1,<4.0.0)
Requires-Dist: poseidon-py (>=0.1.3,<0.2.0)
Requires-Dist: pycryptodome (>=3.10,<4.0)
Requires-Dist: sphinx (>=4.3.1,<8.0.0) ; extra == "docs"
Requires-Dist: typing-extensions (>=3.10.0)
Project-URL: Documentation, https://starknetpy.rtfd.io/
Project-URL: Repository, https://github.com/software-mansion/starknet.py
